{
    "projectData": {
        "basicInfo": {
            "projectName": "上海大学光伏",
            "projectAddress": "上海大学",
            "userName": "shu",
            "remark": "good",
            "lng": "121.416777",
            "lat": "31.217479",
            "projectDate": "2016-06-27T06:08:18.183Z"
        },
        "meteorologyInfo": {
            "type": "db",
            "monthinfos": [
                {
                    "H": 2.63,
                    "temperature": 4.84,
                    "H0": 5.71,
                    "humidity": 73.6,
                    "Kt": 0.46,
                    "Hd": 1.1,
                    "Ws": 76.8,
                    "wind": 6.22,
                    "$$hashKey": "object:383"
                },
                {
                    "H": 3.09,
                    "temperature": 5.88,
                    "H0": 7.05,
                    "humidity": 73.4,
                    "Kt": 0.43,
                    "Hd": 1.41,
                    "Ws": 82.4,
                    "wind": 6.2,
                    "$$hashKey": "object:384"
                },
                {
                    "H": 3.53,
                    "temperature": 9.03,
                    "H0": 8.73,
                    "humidity": 74.9,
                    "Kt": 0.4,
                    "Hd": 1.81,
                    "Ws": 88.9,
                    "wind": 5.68,
                    "$$hashKey": "object:385"
                },
                {
                    "H": 4.28,
                    "temperature": 14,
                    "H0": 10.2,
                    "humidity": 76.9,
                    "Kt": 0.41,
                    "Hd": 2.18,
                    "Ws": 95.9,
                    "wind": 5.42,
                    "$$hashKey": "object:386"
                },
                {
                    "H": 4.84,
                    "temperature": 18.4,
                    "H0": 11.1,
                    "humidity": 79.7,
                    "Kt": 0.43,
                    "Hd": 2.44,
                    "Ws": 101,
                    "wind": 5.01,
                    "$$hashKey": "object:387"
                },
                {
                    "H": 4.58,
                    "temperature": 22.4,
                    "H0": 11.4,
                    "humidity": 84.5,
                    "Kt": 0.39,
                    "Hd": 2.53,
                    "Ws": 104,
                    "wind": 5.2,
                    "$$hashKey": "object:388"
                },
                {
                    "H": 5.17,
                    "temperature": 25.8,
                    "H0": 11.2,
                    "humidity": 87.1,
                    "Kt": 0.45,
                    "Hd": 2.47,
                    "Ws": 103,
                    "wind": 5.37,
                    "$$hashKey": "object:389"
                },
                {
                    "H": 4.78,
                    "temperature": 25.7,
                    "H0": 10.4,
                    "humidity": 86.5,
                    "Kt": 0.45,
                    "Hd": 2.25,
                    "Ws": 98.4,
                    "wind": 5.24,
                    "$$hashKey": "object:390"
                },
                {
                    "H": 4.07,
                    "temperature": 22.6,
                    "H0": 9.19,
                    "humidity": 80.7,
                    "Kt": 0.44,
                    "Hd": 1.92,
                    "Ws": 91.8,
                    "wind": 5.51,
                    "$$hashKey": "object:391"
                },
                {
                    "H": 3.36,
                    "temperature": 17.8,
                    "H0": 7.56,
                    "humidity": 75.1,
                    "Kt": 0.44,
                    "Hd": 1.53,
                    "Ws": 84.8,
                    "wind": 5.44,
                    "$$hashKey": "object:392"
                },
                {
                    "H": 2.79,
                    "temperature": 12.7,
                    "H0": 6.04,
                    "humidity": 73.9,
                    "Kt": 0.46,
                    "Hd": 1.17,
                    "Ws": 78.6,
                    "wind": 5.83,
                    "$$hashKey": "object:393"
                },
                {
                    "H": 2.58,
                    "temperature": 7.27,
                    "H0": 5.29,
                    "humidity": 73.4,
                    "Kt": 0.48,
                    "Hd": 0.99,
                    "Ws": 75.2,
                    "wind": 5.94,
                    "$$hashKey": "object:394"
                }
            ],
            "monthavgs": {
                "H": "3.81",
                "temperature": "15.54",
                "humidity": "78.31",
                "wind": "5.59"
            },
            "lng": "121.416777",
            "lat": "31.217479"
        },
        "componentInfo": {
            "id": 4,
            "公司": "天合",
            "型号": "TSM-DC05A.08",
            "宽度": 992,
            "峰值功率": 275,
            "工作温度上限": 85,
            "工作温度下限": -40,
            "开路电压": 38.7,
            "开路电压温度系数": -0.32,
            "最大功率温度系数": -0.41,
            "最大功率点电压": 31.2,
            "最大功率点电流": 8.82,
            "短路电流": 9.26,
            "短路电流温度系数": 0.05,
            "类型": "单晶",
            "系列": "HoneyM",
            "转换效率": 16.8,
            "重量": 18.6,
            "长度": 1650
        },
        "angleInfo": {
            "dip": 26,
            "bestDipH": 24,
            "bestDipG": 26,
            "az": 0,
            "max": 0.936052025974539,
            "max_H": 48.11315726169288
        },
        "userDesignInfo": {
            "componentDirection": "vertical",
            "designType": "area",
            "rowsPerFixture": 2,
            "colsPerFixture": 1,
            "fbspace": 5.77,
            "lrspace": 0,
            "area": {
                "length": "23",
                "width": "34",
                "numPerRow": 23,
                "rowsNum": 5,
                "fbRestSpace": "5.15",
                "lrRestSpace": "0.18",
                "componentsNum": 230,
                "totalArea": 782,
                "totalCapacity": 63.25
            },
            "capacity": {
                "totalCapacity": "3400",
                "componentsNum": 12364
            }
        },
        "chooseInverter": {
            "type": "group",
            "centralizedInverterInfo": {
                "centralizedInverter": {
                    "MPP电压上限": 850,
                    "MPP电压下限": 460,
                    "id": 2,
                    "厂家": "阳光电源",
                    "启动电压": 500,
                    "型号": "SG500MX",
                    "最大交流输出电流": 1008,
                    "最大效率": 98.7,
                    "最大直流输入功率": 560000,
                    "最大直流输入电流": 1220,
                    "最大输入电压": 1000,
                    "最大输出功率": 550000,
                    "额定交流输出功率": 500000,
                    "额定电网电压": 315
                },
                "serialNumPerBranch": 16,
                "branchNumPerInverter": 111,
                "volumeRatio": 1.05,
                "inverterNumNeeded": 7,
                "totalOpacity": 3916
            },
            "directCurrentInfo": {
                "directCurrent": {
                    "id": 17,
                    "价格上限": 8700,
                    "价格下限": 5200,
                    "厂家": "安科瑞",
                    "型号": "APV-M-4",
                    "有监控单元": true,
                    "有直流断路器": true,
                    "有防雷失效监控": true,
                    "辅助电源": "AC85V-265V/DC330V-880V/DC24V(±10%)",
                    "输入电流上限": 20,
                    "输入路数": "4"
                },
                "num": 196,
                "branches": "4",
                "numPerInverter": 28
            },
            "directDistributionInfo": {
                "directDistribution": {
                    "id": 12,
                    "公司": "深圳永联科技有限公司",
                    "型号": "YLDPG-500",
                    "接入开路电压上限": 1000,
                    "接入直流路数": "8",
                    "输入直流功率上限": 550000,
                    "输入输出总电流上限": "200"
                },
                "num": 28,
                "branches": "8",
                "numPerInverter": 4
            },
            "directCurrentCableInfo": {
                "cables": [
                    {
                        "directCurrentCable": {
                            "id": 31,
                            "允许载流量": 21,
                            "名称": "铜芯聚氯乙烯绝缘电缆",
                            "型号": "228 IEC 01(BV)",
                            "容量": 12000,
                            "导体截面": 1.5
                        },
                        "maxCurrent": 8.82,
                        "branches": 1,
                        "length": "2",
                        "lineDrop": 0.54096,
                        "loss": 0.0010836538461538462
                    },
                    {
                        "directCurrentCable": {
                            "id": 37,
                            "允许载流量": 120,
                            "名称": "铜芯聚氯乙烯绝缘电缆",
                            "型号": "234 IEC 01(BV)",
                            "容量": 67000,
                            "导体截面": 25
                        },
                        "maxCurrent": 35.28,
                        "branches": 1,
                        "length": "4",
                        "lineDrop": 0.2596608,
                        "loss": 0.0005207181243520624
                    },
                    {
                        "directCurrentCable": {
                            "id": 39,
                            "允许载流量": 187,
                            "名称": "铜芯聚氯乙烯绝缘电缆",
                            "型号": "236 IEC 01(BV)",
                            "容量": 105000,
                            "导体截面": 50
                        },
                        "maxCurrent": 163.17,
                        "branches": 6,
                        "length": "6",
                        "lineDrop": 0.9006983999999999,
                        "loss": 0.0018052226473493365
                    }
                ],
                "totalLoss": 0.003409594617855245
            }
        },
        "transformer": {
            "type": "380v"
        },
        "parameters": {
            "AA": 0.9575,
            "AB": 0.45927,
            "AC": 0.42,
            "AD": 0.25,
            "AE": 0.9,
            "AF": 1,
            "AG": 20,
            "AH": 5,
            "AI": 0.17,
            "AJ": 0.86175,
            "AY": 0,
            "BB": 25,
            "BC": 3,
            "BD": 4,
            "BE": 100,
            "DA": 5.6,
            "DB": 0.3,
            "DC": 1.6,
            "DD": 0.1,
            "DE": 0.18,
            "LC": 0.0793,
            "FA": 0.085,
            "HA": 0.005,
            "JA": 0.02,
            "GA": 0.005,
            "GB": 0.0655,
            "GC": 0.5,
            "GD": 10,
            "GF": 0,
            "GG": 20000,
            "GI": 0,
            "GR": 0,
            "GP": 100000,
            "GQ": 0,
            "GO": 0,
            "GS": 0,
            "MM": 0,
            "MY": 0.0655
        },
        "investmentCosts": {
            "data1": {
                "CA": [
                    58367099.99999999,
                    57783428.99999999,
                    57205594.70999999,
                    56633538.762899995,
                    56067203.37527099,
                    55506531.34151828,
                    54951466.0281031,
                    54401951.367822066,
                    53857931.85414384,
                    53319352.535602406,
                    52967444.808867425,
                    52617859.673128895,
                    52270581.79928624,
                    51925595.95941095,
                    51582887.026078835,
                    51242439.97170671,
                    50904239.86789344,
                    50568271.88476534,
                    50234521.29032589,
                    49902973.44980974,
                    49573613.82504099,
                    49246427.97379571,
                    48921401.54916866,
                    48598520.298944145,
                    48277770.06497111
                ],
                "CD": [
                    50297848.425,
                    49794869.940749995,
                    49296921.24134249,
                    48803952.02892907,
                    48315912.508639775,
                    47832753.38355338,
                    47354425.84971785,
                    46880881.59122067,
                    46412072.77530846,
                    45947952.04755537,
                    45644695.5640415,
                    45343440.573318824,
                    45044173.86553492,
                    44746882.318022385,
                    44451552.89472344,
                    44158172.64561826,
                    43866728.70615718,
                    43577208.296696536,
                    43289598.721938334,
                    43003887.37037354,
                    42720061.713729076,
                    42438109.306418456,
                    42158017.78499609,
                    41879774.86761512,
                    41603368.353488855
                ],
                "CE": [
                    42989614.038461536,
                    42559717.89807692,
                    42134120.71909615,
                    41712779.51190519,
                    41295651.71678614,
                    40882695.19961827,
                    40473868.247622095,
                    40069129.56514587,
                    39668438.269494414,
                    39271753.88679946,
                    39012560.31114659,
                    38755077.413093016,
                    38499293.9021666,
                    38245198.5624123,
                    37992780.251900375,
                    37742027.90223783,
                    37492930.51808306,
                    37245477.17666371,
                    36999657.02729772,
                    36755459.29091756,
                    36512873.2595975,
                    36271888.29608415,
                    36032493.83333,
                    35794679.37403002,
                    35558434.49016142
                ],
                "CF": [
                    39105956.99999999,
                    38714897.42999999,
                    38327748.455699995,
                    37944470.97114299,
                    37565026.26143156,
                    23312743.16343768,
                    23079615.7318033,
                    22848819.57448527,
                    22620331.378740415,
                    22394128.06495301,
                    22246326.819724318,
                    22099501.062714137,
                    21953644.35570022,
                    21808750.3029526,
                    21664812.55095311,
                    21521824.788116816,
                    21379780.744515244,
                    21238674.191601444,
                    21098498.941936873,
                    20959248.84892009,
                    0,
                    0,
                    0,
                    0,
                    0
                ],
                "CG": [
                    33423894.87179487,
                    33089655.92307692,
                    32758759.363846153,
                    32431171.77020769,
                    32106860.05250561,
                    19925421.507211693,
                    19726167.292139575,
                    19528905.619218178,
                    19333616.563025996,
                    19140280.397395737,
                    19013954.546772923,
                    18888462.44676422,
                    18763798.594615575,
                    18639957.52389111,
                    18516933.804233428,
                    18394722.041125484,
                    18273316.875654057,
                    18152712.98427474,
                    18032905.078578524,
                    17913887.905059904,
                    0,
                    0,
                    0,
                    0,
                    0
                ],
                "CH": [
                    89403805.42499998,
                    88509767.37074998,
                    87624669.6970425,
                    86748423.00007206,
                    85880938.77007133,
                    71145496.54699105,
                    70434041.58152115,
                    69729701.16570593,
                    69032404.15404887,
                    68342080.11250839,
                    67891022.38376582,
                    67442941.63603297,
                    66997818.22123514,
                    66555632.62097499,
                    66116365.44567655,
                    65679997.43373507,
                    65246509.45067242,
                    64815882.488297984,
                    64388097.66387521,
                    63963136.219293624,
                    42720061.713729076,
                    42438109.306418456,
                    42158017.78499609,
                    41879774.86761512,
                    41603368.353488855
                ],
                "CI": [
                    76413508.9102564,
                    75649373.82115385,
                    74892880.0829423,
                    74143951.28211288,
                    73402511.76929174,
                    60808116.706829965,
                    60200035.53976167,
                    59598035.18436405,
                    59002054.83252041,
                    58412034.2841952,
                    58026514.857919514,
                    57643539.85985723,
                    57263092.49678217,
                    56885156.08630341,
                    56509714.05613381,
                    56136749.94336332,
                    55766247.393737115,
                    55398190.16093846,
                    55032562.105876245,
                    54669347.195977464,
                    36512873.2595975,
                    36271888.29608415,
                    36032493.83333,
                    35794679.37403002,
                    35558434.49016142
                ],
                "CB": 1316928648.418555,
                "CC": 52677145.9367422,
                "CJ": 1134863262.7746894,
                "CK": 45394530.51098758,
                "CL": 969968600.6621282,
                "CM": 38798744.02648513,
                "CN": 521884800.638829,
                "CO": 20875392.02555316,
                "CP": 446055385.16139233,
                "CQ": 17842215.406455692,
                "CR": 1656748063.4135187,
                "CS": 66269922.53654075,
                "CT": 1416023985.8235202,
                "CU": 56640959.43294081,
                "CV": 1416023985.8235202
            },
            "data2": {
                "DA": 5.6,
                "DB": 0.3,
                "DC": 1.6,
                "DD": 0.1,
                "DE": 0.18,
                "DF": 354200000,
                "DG": 18974999.999999996,
                "DH": 101200000,
                "DI": 6325000,
                "DJ": 11385000,
                "DK": 302735042.73504275,
                "DL": 16217948.717948716,
                "DM": 86495726.4957265,
                "DN": 5405982.905982906,
                "DO": 9730769.230769232,
                "DP": 7.779999999999999,
                "DQ": 492085000,
                "DR": 420585470.0854701,
                "DS": 440620042.73504275
            },
            "data3": {
                "EA": 975403943.0884774,
                "EB": 0.6888329243386435
            },
            "data4": {
                "FA": 0.085,
                "FB": 134406250.00000003
            },
            "data5": {
                "GE": 2360039.976372534,
                "GF": 0,
                "GG": 20000,
                "GH": 2685963.9583333335,
                "GI": 0,
                "GR": 0,
                "GK": 60962746.443029836,
                "GO": 0,
                "GP": 100000,
                "GL": 88636810.625,
                "GQ": 0,
                "GS": 0,
                "S1": 63322786.41940237,
                "S2": 0,
                "S3": 120000,
                "S4": 91322774.58333333,
                "S5": 0,
                "S6": 0,
                "GJ": 5066003.934705867,
                "GM": 149699557.06802982,
                "GN": 154765561.0027357
            },
            "data6": {
                "HB": 2360039.976372534,
                "HC": 60962746.44302984,
                "HD": 63322786.419402376
            },
            "data7": {
                "IA": 622909345.6663393,
                "IB": 0.4399002784575521
            },
            "data8": {
                "JA": 0.02,
                "JB": 253291145.6776095
            },
            "data9": {
                "KA": 369618199.9887298,
                "KB": 0.2610253807062245
            },
            "otherdata": {
                "MI": 88636810.625,
                "MX": [
                    16115783.75,
                    14504205.375,
                    12892627,
                    11281048.625,
                    9669470.25,
                    8057891.875,
                    6446313.5,
                    4834735.125,
                    3223156.75,
                    1611578.375,
                    0,
                    0,
                    0,
                    0,
                    0,
                    0,
                    0,
                    0,
                    0,
                    0,
                    0,
                    0,
                    0,
                    0,
                    0
                ],
                "MF": 246042500,
                "MG": [
                    221438250,
                    196834000,
                    172229750,
                    147625500,
                    123021250,
                    98417000,
                    73812750,
                    49208500,
                    24604250,
                    0,
                    0,
                    0,
                    0,
                    0,
                    0,
                    0,
                    0,
                    0,
                    0,
                    0,
                    0,
                    0,
                    0,
                    0,
                    0
                ]
            }
        },
        "emc": {
            "data": {
                "LA": 445360122.68778783,
                "LB": 45357962.74595418,
                "LC": 0.0793,
                "LD": 0.019825,
                "LE": 11339490.686488545,
                "LF": 491660972.51,
                "LG": 489896134.95656663,
                "LH": 489896134.95656663,
                "LI": 44536012.2687788,
                "LJ": 0.09090909090909094,
                "LK": 926127850.8669536,
                "LM": 669696107.9808939,
                "LN": 0.7231141006654616,
                "LO": [
                    11339490.686488545,
                    11339490.686488545,
                    11339490.686488545,
                    11339490.686488545,
                    11339490.686488545,
                    11339490.686488545,
                    11339490.686488545,
                    11339490.686488545,
                    11339490.686488545,
                    11339490.686488545,
                    11339490.686488545,
                    11339490.686488545,
                    11339490.686488545,
                    11339490.686488545,
                    11339490.686488545,
                    11339490.686488545,
                    11339490.686488545,
                    11339490.686488545,
                    11339490.686488545,
                    11339490.686488545,
                    11339490.686488545,
                    11339490.686488545,
                    11339490.686488545,
                    11339490.686488545,
                    11339490.686488545,
                    11339490.686488545,
                    11339490.686488545,
                    11339490.686488545,
                    11339490.686488545,
                    11339490.686488545,
                    11339490.686488545,
                    11339490.686488545,
                    11339490.686488545,
                    11339490.686488545,
                    11339490.686488545,
                    11339490.686488545,
                    11339490.686488545,
                    11339490.686488545,
                    11339490.686488545,
                    11339490.686488545,
                    11339490.686488545,
                    11339490.686488545,
                    11339490.686488545,
                    11339490.686488545,
                    11339490.686488545,
                    11339490.686488545,
                    11339490.686488545,
                    11339490.686488545,
                    11339490.686488545,
                    11339490.686488545,
                    11339490.686488545,
                    11339490.686488545,
                    11339490.686488545,
                    11339490.686488545,
                    11339490.686488545,
                    11339490.686488545,
                    11339490.686488545,
                    11339490.686488545,
                    11339490.686488545,
                    11339490.686488545,
                    11339490.686488545,
                    11339490.686488545,
                    11339490.686488545,
                    11339490.686488545,
                    11339490.686488545,
                    11339490.686488545,
                    11339490.686488545,
                    11339490.686488545,
                    11339490.686488545,
                    11339490.686488545,
                    11339490.686488545,
                    11339490.686488545,
                    11339490.686488545,
                    11339490.686488545,
                    11339490.686488545,
                    11339490.686488545,
                    11339490.686488545,
                    11339490.686488545,
                    11339490.686488545,
                    11339490.686488545,
                    11339490.686488545,
                    11339490.686488545,
                    11339490.686488545,
                    11339490.686488545,
                    11339490.686488545,
                    11339490.686488545,
                    11339490.686488545,
                    11339490.686488545,
                    11339490.686488545,
                    11339490.686488545,
                    11339490.686488545,
                    11339490.686488545,
                    11339490.686488545,
                    11339490.686488545,
                    11339490.686488545,
                    11339490.686488545,
                    11339490.686488545,
                    11339490.686488545,
                    11339490.686488545,
                    11339490.686488545
                ],
                "LP": [
                    9712190.875513934,
                    9679929.656761361,
                    9647028.859347021,
                    9613475.803623939,
                    9579257.558571149,
                    9544360.936810186,
                    9508772.489522813,
                    9472478.501267968,
                    9435464.98469597,
                    9397717.67515793,
                    9359222.025208302,
                    9319963.198998421,
                    9279926.06655893,
                    9239095.197968824,
                    9197454.85740892,
                    9154988.997097418,
                    9111681.251105238,
                    9067514.929048764,
                    9022473.00965752,
                    8976538.134214345,
                    8929692.59986551,
                    8881918.352798207,
                    8833196.981282797,
                    8783509.708577093,
                    8732837.385689998,
                    8681160.484001666,
                    8628459.087737365,
                    8574712.886292122,
                    8519901.166403228,
                    8464002.804167537,
                    8406996.256900523,
                    8348859.55483394,
                    8289570.292648887,
                    8229105.620841016,
                    8167442.236914554,
                    8104556.376401749,
                    8040423.803704279,
                    7975019.802753081,
                    7908319.167483025,
                    7840296.192118741,
                    7770924.661267859,
                    7700177.839817859,
                    7628028.462632612,
                    7554448.7240446685,
                    7479410.267139219,
                    7402884.172825619,
                    7324840.948692251,
                    7245250.517640439,
                    7164082.206293026,
                    7081304.73317315,
                    6996886.196648672,
                    6910794.062637597,
                    6822995.152069752,
                    6733455.628099899,
                    6642140.983067344,
                    6549016.025197019,
                    6454044.865036914,
                    6357190.901626636,
                    6258416.808391749,
                    6157684.5187584795,
                    6054955.211483231,
                    5950189.29569125,
                    5843346.395618693,
                    5734385.335052199,
                    5623264.121459974,
                    5509939.929808282,
                    5394369.086057097,
                    5276507.050328543,
                    5156308.399741671,
                    5033726.810906914,
                    4908715.042073509,
                    4781224.9149229815,
                    4651207.296001694,
                    4518612.077785293,
                    4383388.15936775,
                    4245483.42676758,
                    4104844.732843613,
                    3961417.876812602,
                    3815147.583360777,
                    3665977.4813412684,
                    3513850.082049224,
                    3358706.7570662145,
                    3200487.715665417,
                    3039131.9817688484,
                    2874577.3704477805,
                    2706760.4639572725,
                    2535616.58729559,
                    2361079.7832790893,
                    2183082.787122962,
                    2001557.0005180396,
                    1816432.4651936744,
                    1627637.8359565039,
                    1435100.3531947061,
                    1238745.8148371556,
                    1038498.5477566669,
                    834281.3786063076,
                    626015.6040775422,
                    413620.96056874417,
                    197015.59325238413,
                    -23883.97547102273
                ],
                "LQ": [
                    1627299.810974611,
                    1659561.0297271833,
                    1692461.8271415234,
                    1726014.8828646056,
                    1760233.127917396,
                    1795129.7496783584,
                    1830718.1969657317,
                    1867012.1852205768,
                    1904025.7017925754,
                    1941773.0113306139,
                    1980268.6612802427,
                    2019527.4874901231,
                    2059564.6199296154,
                    2100395.4885197207,
                    2142035.8290796243,
                    2184501.689391127,
                    2227809.435383307,
                    2271975.757439781,
                    2317017.676831024,
                    2362952.552274199,
                    2409798.0866230354,
                    2457572.333690338,
                    2506293.705205748,
                    2555980.977911452,
                    2606653.3007985465,
                    2658330.2024868783,
                    2711031.59875118,
                    2764777.8001964223,
                    2819589.520085316,
                    2875487.8823210075,
                    2932494.4295880217,
                    2990631.1316546043,
                    3049920.3938396573,
                    3110385.0656475285,
                    3172048.449573991,
                    3234934.310086795,
                    3299066.882784266,
                    3364470.883735464,
                    3431171.5190055193,
                    3499194.494369804,
                    3568566.0252206856,
                    3639312.8466706853,
                    3711462.2238559322,
                    3785041.962443876,
                    3860080.419349326,
                    3936606.513662926,
                    4014649.7377962936,
                    4094240.1688481057,
                    4175408.4801955186,
                    4258185.953315395,
                    4342604.489839872,
                    4428696.623850947,
                    4516495.534418792,
                    4606035.058388646,
                    4697349.703421201,
                    4790474.661291526,
                    4885445.82145163,
                    4982299.784861908,
                    5081073.878096796,
                    5181806.167730065,
                    5284535.475005314,
                    5389301.390797295,
                    5496144.290869852,
                    5605105.351436346,
                    5716226.565028571,
                    5829550.756680262,
                    5945121.600431448,
                    6062983.636160001,
                    6183182.2867468735,
                    6305763.8755816305,
                    6430775.644415036,
                    6558265.771565563,
                    6688283.39048685,
                    6820878.608703252,
                    6956102.527120794,
                    7094007.259720964,
                    7234645.953644931,
                    7378072.809675943,
                    7524343.103127768,
                    7673513.205147276,
                    7825640.60443932,
                    7980783.92942233,
                    8139002.970823128,
                    8300358.704719696,
                    8464913.316040764,
                    8632730.222531272,
                    8803874.099192955,
                    8978410.903209455,
                    9156407.899365582,
                    9337933.685970506,
                    9523058.22129487,
                    9711852.85053204,
                    9904390.333293838,
                    10100744.871651389,
                    10300992.138731878,
                    10505209.307882236,
                    10713475.082411002,
                    10925869.7259198,
                    11142475.09323616,
                    11363374.661959568
                ],
                "LR": [
                    488268835.14559203,
                    486609274.1158649,
                    484916812.28872335,
                    483190797.40585876,
                    481430564.27794135,
                    479635434.528263,
                    477804716.3312972,
                    475937704.1460766,
                    474033678.444284,
                    472091905.4329534,
                    470111636.7716732,
                    468092109.2841831,
                    466032544.6642535,
                    463932149.17573375,
                    461790113.3466541,
                    459605611.657263,
                    457377802.22187966,
                    455105826.46443987,
                    452788808.78760886,
                    450425856.23533463,
                    448016058.1487116,
                    445558485.8150213,
                    443052192.10981554,
                    440496211.13190407,
                    437889557.83110553,
                    435231227.62861866,
                    432520196.0298675,
                    429755418.22967106,
                    426935828.7095857,
                    424060340.8272647,
                    421127846.3976767,
                    418137215.2660221,
                    415087294.8721824,
                    411976909.8065349,
                    408804861.3569609,
                    405569927.0468741,
                    402270860.16408986,
                    398906389.2803544,
                    395475217.76134884,
                    391976023.26697904,
                    388407457.24175835,
                    384768144.39508766,
                    381056682.17123175,
                    377271640.20878786,
                    373411559.78943855,
                    369474953.2757756,
                    365460303.5379793,
                    361366063.3691312,
                    357190654.8889357,
                    352932468.9356203,
                    348589864.44578046,
                    344161167.8219295,
                    339644672.2875107,
                    335038637.22912204,
                    330341287.52570087,
                    325550812.8644093,
                    320665367.0429577,
                    315683067.2580958,
                    310601993.379999,
                    305420187.2122689,
                    300135651.73726356,
                    294746350.34646624,
                    289250206.0555964,
                    283645100.7041601,
                    277928874.13913155,
                    272099323.3824513,
                    266154201.78201985,
                    260091218.14585984,
                    253908035.85911298,
                    247602271.98353136,
                    241171496.33911633,
                    234613230.56755078,
                    227924947.17706394,
                    221104068.5683607,
                    214147966.0412399,
                    207053958.78151894,
                    199819312.827874,
                    192441240.01819807,
                    184916896.9150703,
                    177243383.70992303,
                    169417743.1054837,
                    161436959.1760614,
                    153297956.20523825,
                    144997597.50051856,
                    136532684.1844778,
                    127899953.96194653,
                    119096079.86275357,
                    110117668.95954412,
                    100961261.06017855,
                    91623327.37420805,
                    82100269.15291318,
                    72388416.30238114,
                    62484025.9690873,
                    52383281.097435914,
                    42082288.95870404,
                    31577079.650821805,
                    20863604.568410803,
                    9937734.842491003,
                    -1204740.2507451568,
                    -12568114.912704725
                ],
                "sumLO": 1133949068.6488538,
                "LS": 631484818.7795831,
                "sumLQ": 502464249.86927146,
                "LT": 282074917.17466575,
                "LU": 25643174.288605973
            }
        },
        "profitPeriod": {
            "MA": 51464957.26495727,
            "DS": 440620042.73504275,
            "MB": 2380039.976372534,
            "MC": 448046086.64612114,
            "CL": 969968600.6621282,
            "CE": [
                42989614.038461536,
                42559717.89807692,
                42134120.71909615,
                41712779.51190519,
                41295651.71678614,
                40882695.19961827,
                40473868.247622095,
                40069129.56514587,
                39668438.269494414,
                39271753.88679946,
                39012560.31114659,
                38755077.413093016,
                38499293.9021666,
                38245198.5624123,
                37992780.251900375,
                37742027.90223783,
                37492930.51808306,
                37245477.17666371,
                36999657.02729772,
                36755459.29091756,
                36512873.2595975,
                36271888.29608415,
                36032493.83333,
                35794679.37403002,
                35558434.49016142
            ],
            "CQ": 17842215.406455692,
            "CG": [
                33423894.87179487,
                33089655.92307692,
                32758759.363846153,
                32431171.77020769,
                32106860.05250561,
                19925421.507211693,
                19726167.292139575,
                19528905.619218178,
                19333616.563025996,
                19140280.397395737,
                19013954.546772923,
                18888462.44676422,
                18763798.594615575,
                18639957.52389111,
                18516933.804233428,
                18394722.041125484,
                18273316.875654057,
                18152712.98427474,
                18032905.078578524,
                17913887.905059904,
                0,
                0,
                0,
                0,
                0
            ],
            "CT": 1416023985.8235202,
            "CZ": [
                76413508.9102564,
                75649373.82115385,
                74892880.0829423,
                74143951.28211288,
                73402511.76929174,
                60808116.706829965,
                60200035.53976167,
                59598035.18436405,
                59002054.83252041,
                58412034.2841952,
                58026514.857919514,
                57643539.85985723,
                57263092.49678217,
                56885156.08630341,
                56509714.05613381,
                56136749.94336332,
                55766247.393737115,
                55398190.16093846,
                55032562.105876245,
                54669347.195977464,
                36512873.2595975,
                36271888.29608415,
                36032493.83333,
                35794679.37403002,
                35558434.49016142
            ],
            "ME": 256431742.88605973,
            "MD": 10257269.71544239,
            "MM": 0,
            "sumMM": 0,
            "MI": 88636810.625,
            "MX": [
                16115783.75,
                14504205.375,
                12892627,
                11281048.625,
                9669470.25,
                8057891.875,
                6446313.5,
                4834735.125,
                3223156.75,
                1611578.375,
                0,
                0,
                0,
                0,
                0,
                0,
                0,
                0,
                0,
                0,
                0,
                0,
                0,
                0,
                0
            ],
            "MF": 246042500,
            "MG": [
                221438250,
                196834000,
                172229750,
                147625500,
                123021250,
                98417000,
                73812750,
                49208500,
                24604250,
                0,
                0,
                0,
                0,
                0,
                0,
                0,
                0,
                0,
                0,
                0,
                0,
                0,
                0,
                0,
                0
            ],
            "ML": 1070955432.3124605,
            "MJ": -448046086.64612114,
            "MK": [
                50040455.44481401,
                50887898.73071146,
                51742983.36749992,
                52605632.94167049,
                53475771.803849354,
                42492955.116387576,
                43496452.32431928,
                44506030.34392166,
                45521628.36707802,
                46543186.19375281,
                47769245.142477125,
                47386270.14441484,
                47005822.78133978,
                46627886.37086102,
                46252444.34069142,
                45879480.22792093,
                45508977.678294726,
                45140920.44549607,
                44775292.390433855,
                44412077.480535075,
                26255603.544155113,
                26014618.58064176,
                25775224.11788761,
                25537409.658587627,
                25301164.77471903
            ],
            "MR": 17921843.465844847,
            "MO": [
                24604250,
                24604250,
                24604250,
                24604250,
                24604250,
                24604250,
                24604250,
                24604250,
                24604250,
                24604250,
                0,
                0,
                0,
                0,
                0,
                0,
                0,
                0,
                0,
                0,
                0,
                0,
                0,
                0,
                0
            ],
            "MT": 622909345.6663394,
            "MS": [
                32118611.978969164,
                32966055.264866613,
                33821139.90165507,
                34683789.475825645,
                35553928.33800451,
                24571111.65054273,
                25574608.858474433,
                26584186.878076814,
                27599784.901233174,
                28621342.727907963,
                29847401.676632278,
                29464426.678569995,
                29083979.315494932,
                28706042.905016176,
                28330600.87484657,
                27957636.76207608,
                27587134.21244988,
                27219076.97965122,
                26853448.924589008,
                26490234.014690228,
                8333760.078310266,
                8092775.114796914,
                7853380.652042761,
                7615566.19274278,
                7379321.308874182
            ],
            "MW": 0.43990027845755214,
            "MV": [
                0.7471249206897645,
                0.7745835003844374,
                0.8027019271895368,
                0.8314907297397093,
                0.8609605820448235,
                0.6010149656369073,
                0.6318795303183551,
                0.6634580577762554,
                0.6957618223770053,
                0.7288022534060682,
                0.7650715933172,
                0.7602726828411839,
                0.7554418891266521,
                0.7505790003461693,
                0.7456838032649503,
                0.7407560832315105,
                0.7357956241682534,
                0.7308022085619951,
                0.7257756174544263,
                0.7207156304325133,
                0.22824169489646273,
                0.22311424893946302,
                0.21795273700368742,
                0.21275693275990268,
                0.2075266083751789
            ],
            "MP": -202003586.64612114,
            "MQ": [
                -176567381.20130712,
                -150283732.47059566,
                -123144999.10309574,
                -95143616.16142525,
                -66272094.35757589,
                -48383389.24118832,
                -29491186.916869037,
                -9589406.572947375,
                11327971.794130646,
                33266907.987883456,
                81036153.13036057,
                128422423.27477542,
                175428246.0561152,
                222056132.42697623,
                268308576.76766765,
                314188056.9955886,
                359697034.6738833,
                404837955.1193794,
                449613247.50981325,
                494025324.99034834,
                520280928.53450346,
                546295547.1151452,
                572070771.2330328,
                597608180.8916204,
                622909345.6663394
            ]
        }
    },
    "projectSetting": {
        "isFinished": {
            "basicInfo": true,
            "meteorology": true,
            "chooseComponent": true,
            "confirmAngle": true,
            "userDesign": true,
            "chooseInverter": true,
            "selectTransformer": true,
            "efficiencyAnalysis": true,
            "benefit": true,
            "report": true
        }
    }
}